skrough/__init__.py
skrough/algorithms/__init__.py
skrough/algorithms/bireduct_ordering.py
skrough/algorithms/bireducts.py
skrough/algorithms/constants.py
skrough/algorithms/exceptions.py
skrough/algorithms/hooks/__init__.py
skrough/algorithms/hooks/common/process_elements.py
skrough/algorithms/hooks/filter_hooks.py
skrough/algorithms/hooks/finalize_hooks.py
skrough/algorithms/hooks/helpers.py
skrough/algorithms/hooks/init_hooks.py
skrough/algorithms/hooks/inner_init_hooks.py
skrough/algorithms/hooks/inner_process_hooks.py
skrough/algorithms/hooks/inner_stop_hooks.py
skrough/algorithms/hooks/pre_candidates_hooks.py
skrough/algorithms/hooks/prepare_result_hooks.py
skrough/algorithms/hooks/select_hooks.py
skrough/algorithms/hooks/stop_hooks.py
skrough/algorithms/key_names.py
skrough/algorithms/meta/__init__.py
skrough/algorithms/meta/aggregates.py
skrough/algorithms/meta/describe.py
skrough/algorithms/meta/helpers.py
skrough/algorithms/meta/processing.py
skrough/algorithms/meta/stage.py
skrough/algorithms/meta/visual_block.py
skrough/algorithms/reduct_ordering.py
skrough/algorithms/reducts.py
skrough/algorithms/reusables/__init__.py
skrough/algorithms/reusables/attrs_daar.py
skrough/algorithms/reusables/attrs_greedy.py
skrough/algorithms/reusables/attrs_reduction.py
skrough/algorithms/reusables/objs_choose.py
skrough/attrs_checks.py
skrough/checks.py
skrough/dataprep.py
skrough/disorder_measures/__init__.py
skrough/disorder_measures/disorder_measures.py
skrough/disorder_measures/gini_impurity_cython.pyx
skrough/disorder_score.py
skrough/estimators/__init__.py
skrough/estimators/base.py
skrough/feature_importance.py
skrough/homogeneity.py
skrough/instances.py
skrough/logs.py
skrough/permutations.py
skrough/predict/__init__.py
skrough/predict/aggregate.py
skrough/predict/helpers.py
skrough/predict/predict_attrs.py
skrough/predict/predict_attrs_ensemble.py
skrough/predict/predict_objs_attrs.py
skrough/predict/predict_objs_attrs_ensemble.py
skrough/ranks.py
scikit_rough-0.1.3.dist-info/LICENSE
scikit_rough-0.1.3.dist-info/METADATA
scikit_rough-0.1.3.dist-info/WHEEL
scikit_rough-0.1.3.dist-info/RECORD
