Metadata-Version: 2.1
Name: scikit-rough
Version: 0.1.3
Summary: 
License: MIT
Author: sebov
Author-email: 12091011+sebov@users.noreply.github.com
Requires-Python: >=3.9,<4.0
Classifier: License :: OSI Approved :: MIT License
Classifier: Programming Language :: Python :: 3
Classifier: Programming Language :: Python :: 3.9
Classifier: Programming Language :: Python :: 3.10
Classifier: Programming Language :: Python :: 3.11
Requires-Dist: attrs (>=23.1.0,<24.0.0)
Requires-Dist: docstring-parser (>=0.15)
Requires-Dist: joblib (>=1.1.0,<2.0.0)
Requires-Dist: more-itertools (>=8.14.0,<9.0.0)
Requires-Dist: numba (>=0.56.0)
Requires-Dist: numpy (>=1.22.4,<2.0.0)
Requires-Dist: pandas (>=2.0.0,<3.0.0)
Requires-Dist: scikit-learn (>=1.1.1,<2.0.0)
